gias3.applications-3.0.1-py3.11-nspkg.pth
gias3/applications/__init__.py
gias3/applications/general.py
gias3/applications/giashmfinp2surf.py
gias3/applications/giasinpsampledicom.py
gias3/applications/giaspcreg.py
gias3/applications/giasrbfreg.py
gias3/applications/giasrigidreg.py
gias3/applications/giassurfacedistance.py
gias3/applications/giastrainpcashapemodel.py
gias3.applications-3.0.1.dist-info/LICENSE
gias3.applications-3.0.1.dist-info/METADATA
gias3.applications-3.0.1.dist-info/WHEEL
gias3.applications-3.0.1.dist-info/entry_points.txt
gias3.applications-3.0.1.dist-info/namespace_packages.txt
gias3.applications-3.0.1.dist-info/top_level.txt
gias3.applications-3.0.1.dist-info/RECORD
